CHANGES.txt
MANIFEST.in
README.rst
main.py
setup.cfg
setup.py
jtk/__init__.py
jtk/di/__init__.py
jtk/di/dye.py
pyDye.egg-info/PKG-INFO
pyDye.egg-info/SOURCES.txt
pyDye.egg-info/dependency_links.txt
pyDye.egg-info/top_level.txt