Metadata-Version: 1.1
Name: pyDye
Version: 15.10.7
Summary: Rudimentary dependency Injection framework
Home-page: https://github.com/jtkSource/pyDye
Author: Jubin Thomas Kuriakose
Author-email: jubin.kuriakose@gmail.com
License: MIT
Keywords: Dependency Injection Framework
Platform: UNKNOWN
Classifier: Development Status :: 5 - Production/Stable
Classifier: Intended Audience :: Developers
Classifier: Topic :: Software Development :: Libraries :: Python Modules
Classifier: License :: OSI Approved :: MIT License
Classifier: Programming Language :: Python :: 2
Classifier: Programming Language :: Python :: 2.6
Classifier: Programming Language :: Python :: 2.7
Classifier: Programming Language :: Python :: 3
Classifier: Programming Language :: Python :: 3.2
Classifier: Programming Language :: Python :: 3.3
Classifier: Programming Language :: Python :: 3.4
